bitarray/__init__.py
bitarray/__init__.pyi
bitarray/_bitarray.cp310-win32.pyd
bitarray/_util.cp310-win32.pyd
bitarray/bitarray.h
bitarray/py.typed
bitarray/pythoncapi_compat.h
bitarray/test_281.pickle
bitarray/test_bitarray.py
bitarray/test_util.py
bitarray/util.py
bitarray/util.pyi
bitarray-3.7.2.dist-info/licenses/LICENSE
bitarray-3.7.2.dist-info/METADATA
bitarray-3.7.2.dist-info/WHEEL
bitarray-3.7.2.dist-info/top_level.txt
bitarray-3.7.2.dist-info/RECORD
